pyonos/__init__.py
pyonos/api.py
pyonos-0.2.0.dist-info/LICENSE
pyonos-0.2.0.dist-info/METADATA
pyonos-0.2.0.dist-info/WHEEL
pyonos-0.2.0.dist-info/top_level.txt
pyonos-0.2.0.dist-info/RECORD
