Metadata-Version: 2.1
Name: pyonos
Version: 0.2.0
Summary: Wrapper around the IONOS DNS, Domains & SSL API.
Home-page: https://github.com/aaronlyy/pyonos
Author: aaronlyy (Aaron Levi)
Author-email: <aaronlevican@gmail.com>
License: UNKNOWN
Keywords: dns,ssl,domain,domains,ipv4,ipv6,txt,cname,api,ionos
Platform: UNKNOWN
Classifier: Intended Audience :: Developers
Classifier: Programming Language :: Python :: 3.6
Classifier: Programming Language :: Python :: 3.7
Classifier: Programming Language :: Python :: 3.8
Classifier: Programming Language :: Python :: 3.9
Classifier: Programming Language :: Python :: 3.10
Classifier: Programming Language :: Python :: 3.11
Classifier: Programming Language :: Python :: 3 :: Only
Classifier: Topic :: Software Development :: Libraries
Classifier: Operating System :: Unix
Classifier: Operating System :: MacOS :: MacOS X
Classifier: Operating System :: Microsoft :: Windows
License-File: LICENSE
Requires-Dist: requests
